.bumpversion.cfg
.virtualenv.dev-requirements.txt
.virtualenv.requirements.txt
LICENSE
MANIFEST.in
Makefile
README.rst
setup.cfg
setup.py
tox.ini
doc/build/man/kiwi::system::boxbuild.8
kiwi_boxed_plugin/__init__.py
kiwi_boxed_plugin/box_build.py
kiwi_boxed_plugin/box_config.py
kiwi_boxed_plugin/box_download.py
kiwi_boxed_plugin/defaults.py
kiwi_boxed_plugin/exceptions.py
kiwi_boxed_plugin/plugin_config.py
kiwi_boxed_plugin/plugin_config_schema.py
kiwi_boxed_plugin/version.py
kiwi_boxed_plugin.egg-info/PKG-INFO
kiwi_boxed_plugin.egg-info/SOURCES.txt
kiwi_boxed_plugin.egg-info/dependency_links.txt
kiwi_boxed_plugin.egg-info/entry_points.txt
kiwi_boxed_plugin.egg-info/not-zip-safe
kiwi_boxed_plugin.egg-info/requires.txt
kiwi_boxed_plugin.egg-info/top_level.txt
kiwi_boxed_plugin/config/__init__.py
kiwi_boxed_plugin/config/kiwi_boxed_plugin.yml
kiwi_boxed_plugin/tasks/__init__.py
kiwi_boxed_plugin/tasks/system_boxbuild.py
kiwi_boxed_plugin/utils/dir_files.py
kiwi_boxed_plugin/utils/fetch_files.py
package/python-kiwi_boxed_plugin-rpmlintrc
package/python-kiwi_boxed_plugin-spec-template
package/python-kiwi_boxed_plugin.changes