Metadata-Version: 2.1
Name: kiwi_boxed_plugin
Version: 0.2.41
Summary: KIWI - Boxed Build Plugin
Home-page: https://github.com/OSInside/kiwi-boxed-plugin
Download-URL: https://download.opensuse.org/repositories/Virtualization:/Appliances:/Builder
Author: Marcus Schaefer
Author-email: ms@suse.com
License: GPLv3+
Classifier: Development Status :: 5 - Production/Stable
Classifier: Intended Audience :: Developers
Classifier: License :: OSI Approved :: GNU General Public License v3 or later (GPLv3+)
Classifier: Operating System :: POSIX :: Linux
Classifier: Programming Language :: Python :: 3.6
Classifier: Programming Language :: Python :: 3.7
Classifier: Topic :: System :: Operating System
License-File: LICENSE
Requires-Dist: docopt
Requires-Dist: kiwi>=9.21.21
Requires-Dist: requests
Requires-Dist: PyYAML
Requires-Dist: cerberus
Requires-Dist: progressbar2
